LICENSE.txt
MANIFEST.in
README.md
formulation.png
setup.cfg
setup.py
l0bnb/__init__.py
l0bnb/gensynthetic.py
l0bnb/regpath.py
l0bnb/tree.py
l0bnb/utilities.py
l0bnb/viz.py
l0bnb.egg-info/PKG-INFO
l0bnb.egg-info/SOURCES.txt
l0bnb.egg-info/dependency_links.txt
l0bnb.egg-info/requires.txt
l0bnb.egg-info/top_level.txt
l0bnb/node/__init__.py
l0bnb/node/_utils.py
l0bnb/node/core.py
l0bnb/relaxation/__init__.py
l0bnb/relaxation/_coordinate_descent.py
l0bnb/relaxation/_cost.py
l0bnb/relaxation/_utils.py
l0bnb/relaxation/core.py
l0bnb/relaxation/gurobi.py
l0bnb/relaxation/mosek.py
test/__init__.py
test/test_objective.py
test/test_preprocessing.py