Metadata-Version: 2.1
Name: l0bnb
Version: 1.0.0
Summary: Scalable algorithms for L0 L2-regularized regression
Home-page: https://github.com/alisaab/l0bnb
Author: Hussein Hazimeh, Rahul Mazumder, Ali Saab
Author-email: alikassemsaab@gmail.com
License: MIT
Download-URL: https://github.com/alisaab/l0bnb/archive/1.0.0.tar.gz
Platform: UNKNOWN
